zzl_mcp_demo/__init__.py
zzl_mcp_demo-0.1.0.dist-info/METADATA
zzl_mcp_demo-0.1.0.dist-info/WHEEL
zzl_mcp_demo-0.1.0.dist-info/entry_points.txt
zzl_mcp_demo-0.1.0.dist-info/RECORD
