Metadata-Version: 2.4
Name: zzl-mcp-demo
Version: 0.1.0
Summary: Add your description here
Author-email: 张志林 <zhangzhilin1@xiaomi.com>
Requires-Python: >=3.13
Requires-Dist: mcp[cli]>=1.13.0
